{
    "configurations": [
        {
            "name": "Win32",
            "includePath": [
                "${workspaceFolder}/",
                "C:/Program Files (x86)/Microsoft Visual Studio/2019/Enterprise/VC/Tools/MSVC/14.20.27508/include",
                "C:/Program Files (x86)/Microsoft Visual Studio/2019/Enterprise/VC/Tools/MSVC/14.20.27508/atlmfc/include",
                "C:/Program Files (x86)/Microsoft Visual Studio/2019/Enterprise/VC/Auxiliary/VS/include",
                "C:/Program Files (x86)/Windows Kits/10/Include/10.0.17763.0/ucrt",
                "C:/Program Files (x86)/Windows Kits/10/Include/10.0.17763.0/um",
                "C:/Program Files (x86)/Windows Kits/10/Include/10.0.17763.0/shared",
                "C:/Program Files (x86)/Windows Kits/10/Include/10.0.17763.0/winrt",
                "C:/Program Files (x86)/Windows Kits/10/Include/10.0.17763.0/cppwinrt",
                "C:/Program Files (x86)/Windows Kits/NETFXSDK/4.7.2/Include/um"
            ],
            "defines": [
                "_DEBUG",
                "UNICODE",
                "_UNICODE"
            ],
            "intelliSenseMode": "msvc-x64"
        }
    ],
    "version": 4
}